tracmarkdown/__init__.py
tracmarkdown/macro.py
TracMarkdownMacro-0.11.9.dist-info/COPYING
TracMarkdownMacro-0.11.9.dist-info/METADATA
TracMarkdownMacro-0.11.9.dist-info/WHEEL
TracMarkdownMacro-0.11.9.dist-info/entry_points.txt
TracMarkdownMacro-0.11.9.dist-info/top_level.txt
TracMarkdownMacro-0.11.9.dist-info/RECORD
