Metadata-Version: 2.1
Name: TracMarkdownMacro
Version: 0.11.9
Summary: Implements Markdown syntax WikiProcessor as a Trac macro.
Home-page: https://trac-hacks.org/wiki/MarkdownMacro
Author: Douglas Clifton
Author-email: dwclifton@gmail.com
Maintainer: Ryan J Ollos
Maintainer-email: ryan.j.ollos@gmail.com
License: BSD 3-Clause
Keywords: 0.11 dwclifton processor macro wiki
Platform: UNKNOWN
Classifier: Development Status :: 4 - Beta
Classifier: Environment :: Plugins
Classifier: Environment :: Web Environment
Classifier: Framework :: Trac
Classifier: License :: OSI Approved :: BSD License
Classifier: Natural Language :: English
Classifier: Operating System :: OS Independent
Classifier: Programming Language :: Python :: 2
Classifier: Programming Language :: Python :: 2.7
Classifier: Programming Language :: Python :: 3
Requires-Dist: Trac
Requires-Dist: Markdown (<3.2)
